urwid_todos
