Metadata-Version: 1.0
Name: urwid-todos
Version: 0.2.0
Summary: Urwid Components using the Pydux state container
Home-page: http://github.com/benjamin9999/urwid_todos/
Author: Benjamin Yates
Author-email: benjamin@rqdq.com
License: MIT
Platform: UNKNOWN
